mcp_package/__init__.py
mcp_package/main.py
mcp_package-0.1.1.dist-info/METADATA
mcp_package-0.1.1.dist-info/WHEEL
mcp_package-0.1.1.dist-info/licenses/LICENSE
mcp_package-0.1.1.dist-info/RECORD
