Metadata-Version: 2.4
Name: mcp-package
Version: 0.1.1
Summary: MCP Server built with FastAPI MCP
Author-email: madhurya <madhurya3199@gmail.com>
License-File: LICENSE
Requires-Python: >=3.9
Requires-Dist: fastapi-mcp>=0.1.0
Requires-Dist: fastapi>=0.100
Requires-Dist: uvicorn[standard]>=0.22.0
